quickcolors/__init__.py
quicolor/__init__.py
quickcolors-10.0.9.dist-info/LICENSE
quickcolors-10.0.9.dist-info/METADATA
quickcolors-10.0.9.dist-info/WHEEL
quickcolors-10.0.9.dist-info/top_level.txt
quickcolors-10.0.9.dist-info/RECORD
